[
    {
        "pageTitle": "Welcome.",
        "contentAbove": "We deeply appreciate your participation in our study.||Enter the ID you were given when you joined:",
        "contentBelow": "This application is solely for the use of informed and consenting subjects in this IRB-moderated app.",
        "systemImage": "hand.wave",
        "proceedTitle": "Done"
    },
    
    {
        "pageTitle": "Thanks!",
        "contentAbove": "That concludes your session with Walk Test.",
        "contentBelow": "You can close the app now.",
        "systemImage": "hand.wave",
        "proceedTitle": "Done"
    }
]
